oddoreven/__init__.py
oddoreven/checker.py
oddoreven_checker_hafizmdph-0.1.0.dist-info/licenses/LICENSE
oddoreven_checker_hafizmdph-0.1.0.dist-info/METADATA
oddoreven_checker_hafizmdph-0.1.0.dist-info/WHEEL
oddoreven_checker_hafizmdph-0.1.0.dist-info/entry_points.txt
oddoreven_checker_hafizmdph-0.1.0.dist-info/top_level.txt
oddoreven_checker_hafizmdph-0.1.0.dist-info/RECORD
